LICENSE
MANIFEST.in
README.md
setup.py
./README.md
AlphaEdge.egg-info/PKG-INFO
AlphaEdge.egg-info/SOURCES.txt
AlphaEdge.egg-info/dependency_links.txt
AlphaEdge.egg-info/requires.txt
AlphaEdge.egg-info/top_level.txt
alphaedge/__init__.py
alphaedge/api/__init__.py
alphaedge/api/chain.py
alphaedge/api/quantum.py
alphaedge/plugins/__init__.py
alphaedge/plugins/chain/__init__.py
alphaedge/plugins/chain/engine.py
alphaedge/plugins/chain/alpha_s1/__init__.py
alphaedge/plugins/chain/alpha_s1/launcher.py
alphaedge/plugins/chain/alpha_s2/__init__.py
alphaedge/plugins/chain/alpha_s2/launcher.py
alphaedge/plugins/chain/atom/__init__.py
alphaedge/plugins/chain/atom/launcher.py
alphaedge/plugins/quantum/__init__.py
alphaedge/plugins/quantum/base.py
alphaedge/plugins/quantum/constraint.py
alphaedge/plugins/quantum/creator.py
alphaedge/plugins/quantum/optimizer.py
alphaedge/plugins/quantum/predictor.py
alphaedge/plugins/quantum/trainer.py
requirements/py3.txt