Metadata-Version: 2.1
Name: AlphaEdge
Version: 0.1.9
Summary: AlphaEdge0.1.9
Home-page: https://github.com/flaght
Author: flaght
Author-email: flaght@gmail.com
License-File: LICENSE
